universal_dng_converter/__init__.py
universal_dng_converter/cli.py
universal_dng_converter/converter.py
universal_dng_converter-1.0.1.dist-info/licenses/LICENSE
universal_dng_converter-1.0.1.dist-info/METADATA
universal_dng_converter-1.0.1.dist-info/WHEEL
universal_dng_converter-1.0.1.dist-info/entry_points.txt
universal_dng_converter-1.0.1.dist-info/top_level.txt
universal_dng_converter-1.0.1.dist-info/RECORD
