Metadata-Version: 2.4
Name: universal-dng-converter
Version: 1.0.1
Summary: Professional multi-format image converter with DNG output support
Author-email: Elías Gabriel Ferrer Jorge <gabrielferrerjorge@gmail.com>
License: MIT
Project-URL: Homepage, https://github.com/dot-gabriel-ferrer/universal-dng-converter
Project-URL: Bug Reports, https://github.com/dot-gabriel-ferrer/universal-dng-converter/issues
Project-URL: Source, https://github.com/dot-gabriel-ferrer/universal-dng-converter
Keywords: dng,image,converter,fits,astronomy,photography
Classifier: Development Status :: 4 - Beta
Classifier: Intended Audience :: Developers
Classifier: Intended Audience :: Science/Research
Classifier: License :: OSI Approved :: MIT License
Classifier: Operating System :: OS Independent
Classifier: Programming Language :: Python :: 3
Classifier: Programming Language :: Python :: 3.8
Classifier: Programming Language :: Python :: 3.9
Classifier: Programming Language :: Python :: 3.10
Classifier: Programming Language :: Python :: 3.11
Classifier: Programming Language :: Python :: 3.12
Classifier: Topic :: Multimedia :: Graphics :: Graphics Conversion
Classifier: Topic :: Scientific/Engineering :: Astronomy
Classifier: Topic :: Software Development :: Libraries :: Python Modules
Requires-Python: >=3.8
License-File: LICENSE
Requires-Dist: astropy>=5.0
Requires-Dist: pillow>=8.0.0
Requires-Dist: tifffile>=2021.1.11
Requires-Dist: numpy>=1.20.0
Requires-Dist: imagecodecs>=2021.1.11
Provides-Extra: dev
Requires-Dist: pytest>=6.0; extra == "dev"
Requires-Dist: pytest-cov>=2.0; extra == "dev"
Requires-Dist: black>=21.0; extra == "dev"
Requires-Dist: flake8>=3.8; extra == "dev"
Requires-Dist: mypy>=0.910; extra == "dev"
Requires-Dist: pre-commit>=2.15; extra == "dev"
Requires-Dist: tox>=3.24; extra == "dev"
Provides-Extra: exr
Requires-Dist: opencv-python>=4.5.0; extra == "exr"
Dynamic: license-file
